mdap/__init__.py
mdap/__main__.py
mdap/command_line.py
mdap/md_pdist.py
mdap/md_plot.py
mdap/styles/__init__.py
mdap/styles/default.mplstyle
mdap/tests/__init__.py
mdap/tests/make_md_pdist_test_data.py
mdap/tests/test_md_pdist.py
styles/__init__.py
wedap/__init__.py
wedap/__main__.py
wedap/command_line.py
wedap/h5_gif.py
wedap/h5_pdist.py
wedap/h5_plot.py
wedap/styles/__init__.py
wedap/styles/default.mplstyle
wedap/tests/__init__.py
wedap/tests/make_h5_pdist_test_data.py
wedap/tests/make_h5_plot_test_data.py
wedap/tests/test_h5_pdist.py
wedap/tests/test_h5_plot.py
wekap/__init__.py
wekap/__main__.py
wekap/bootstrap.py
wekap/command_line.py
wekap/kinetics.py
wekap/data/__init__.py
wekap/data/ppf.py
wekap/error/GetAvg_CR.py
wekap/error/__init__.py
wekap/error/bootstrap.py
wekap/styles/__init__.py
wekap/styles/default.mplstyle
wedap-1.0.5.dist-info/LICENSE
wedap-1.0.5.dist-info/METADATA
wedap-1.0.5.dist-info/WHEEL
wedap-1.0.5.dist-info/entry_points.txt
wedap-1.0.5.dist-info/top_level.txt
wedap-1.0.5.dist-info/RECORD
