Metadata-Version: 2.1
Name: wedap
Version: 1.0.5
Summary: Weighted Ensemble Data Analysis and Plotting
Home-page: https://github.com/darianyang/wedap
Author: Darian T. Yang
Author-email: dty7@pitt.edu
License: BSD 3-Clause License
Project-URL: Documentation, https://darianyang.github.io/wedap
Classifier: Programming Language :: Python :: 3
Classifier: License :: OSI Approved :: BSD License
Classifier: Operating System :: OS Independent
Classifier: Topic :: Scientific/Engineering :: Chemistry
License-File: LICENSE
Requires-Dist: numpy
Requires-Dist: matplotlib
Requires-Dist: h5py
Requires-Dist: gif
Requires-Dist: tqdm
